json_wrapper.py
json_wrapper-1.2.0.dist-info/LICENSE
json_wrapper-1.2.0.dist-info/METADATA
json_wrapper-1.2.0.dist-info/WHEEL
json_wrapper-1.2.0.dist-info/top_level.txt
json_wrapper-1.2.0.dist-info/RECORD
