Metadata-Version: 2.1
Name: json-wrapper
Version: 1.2.0
Summary: Easy to use JSON wrapper packed with features.
Home-page: https://github.com/RGBCube/json_wrapper
Author: RGBCube
License: CC0 1.0 Universal
Platform: UNKNOWN
License-File: LICENSE
